doapfiend_vcs.py
setup.py
doapfiend_vcs.egg-info/PKG-INFO
doapfiend_vcs.egg-info/SOURCES.txt
doapfiend_vcs.egg-info/dependency_links.txt
doapfiend_vcs.egg-info/entry_points.txt
doapfiend_vcs.egg-info/requires.txt
doapfiend_vcs.egg-info/top_level.txt