Metadata-Version: 1.0
Name: doapfiend-vcs
Version: 0.1.0
Summary: Doapfiend plugin. Find CVS, SVN, etc. repo and run cmds.
Home-page: http://trac.doapspace.org/doapfiend/wiki/DfVCS
Author: Rob Cakebread
Author-email: rob@doapspace.org
License: BSD-2
Keywords: doapfiend.plugin doap rdf svn cvs git mercurial bazaar doapfiend semantic web
Platform: UNKNOWN
Classifier: Development Status :: 2 - Pre-Alpha
Classifier: Intended Audience :: Developers
Classifier: Programming Language :: Python
Classifier: Topic :: Software Development :: Libraries :: Python Modules
